computerai/__init__.py
computerai-0.1.0.dist-info/METADATA
computerai-0.1.0.dist-info/WHEEL
computerai-0.1.0.dist-info/top_level.txt
computerai-0.1.0.dist-info/RECORD
